awsnap/__init__.py
awsnap/awsnap.py
awsnap/pipeline/__init__.py
awsnap/pipeline/cloudformation.py
awsnap/pipeline/command_handler.py
awsnap/pipeline/synth.py
awsnap-1.3.26.dist-info/LICENSE
awsnap-1.3.26.dist-info/METADATA
awsnap-1.3.26.dist-info/WHEEL
awsnap-1.3.26.dist-info/entry_points.txt
awsnap-1.3.26.dist-info/RECORD
