Metadata-Version: 2.1
Name: awsnap
Version: 1.3.26
Summary: AWSnap: an AWS Utility to help manage your projects and sso sessions.
Home-page: https://github.com/aphexlog/AWSnap
License: MIT
Author: Aaron West
Author-email: aphexlog@gmail.com
Requires-Python: >=3.11,<4.0
Classifier: License :: OSI Approved :: MIT License
Classifier: Programming Language :: Python :: 3
Classifier: Programming Language :: Python :: 3.11
Classifier: Programming Language :: Python :: 3.12
Requires-Dist: aws-cdk-lib (>=2.126.0,<3.0.0)
Requires-Dist: boto3 (>=1.34.36,<2.0.0)
Requires-Dist: boto3-stubs (>=1.34.36,<2.0.0)
Requires-Dist: gitpython (>=3.1.41,<4.0.0)
Requires-Dist: setuptools (>=69.0.3,<70.0.0)
Project-URL: Repository, https://github.com/aphexlog/AWSnap
